NIRCAM_Gsim/NIRISS_grism_seed_disperser.py
NIRCAM_Gsim/__init__.py
NIRCAM_Gsim/grism_seed_disperser.py
NIRCAM_Gsim/disperse/__init__.py
NIRCAM_Gsim/disperse/disperse.py
NIRCAM_Gsim/observations/__init__.py
NIRCAM_Gsim/observations/observations.py
NIRCAM_Gsim/polyclip/__init__.py
NIRCAM_Gsim/polyclip/polyclip.py
NIRCAM_Gsim/polyclip/polyclip_c.cpython-311-darwin.so
NIRCAM_Gsim-1.71.dist-info/METADATA
NIRCAM_Gsim-1.71.dist-info/PKG-INFO (Nor Pirzkal's conflicted copy 2024-01-05 1)
NIRCAM_Gsim-1.71.dist-info/PKG-INFO (Nor Pirzkal's conflicted copy 2024-01-05)
NIRCAM_Gsim-1.71.dist-info/SOURCES (Nor Pirzkal's conflicted copy 2024-01-05 1).txt
NIRCAM_Gsim-1.71.dist-info/SOURCES (Nor Pirzkal's conflicted copy 2024-01-05).txt
NIRCAM_Gsim-1.71.dist-info/WHEEL
NIRCAM_Gsim-1.71.dist-info/top_level.txt
NIRCAM_Gsim-1.71.dist-info/RECORD
