Metadata-Version: 2.1
Name: NIRCAM_Gsim
Version: 1.71
Summary: NIRCAM Grism simulator, includes J.D. Smith polyclip C code
Home-page: https://github.com/npirzkal/GRISM_NIRCAM
Author: Nor Pirzkal
Author-email: npirzkal@mac.com
Requires-Dist: tqdm >4.0.0
Requires-Dist: grismconf >=1.24
